[{"__symbolic":"module","version":4,"metadata":{"FilteringService":{"__symbolic":"class","decorators":[{"__symbolic":"call","expression":{"__symbolic":"reference","module":"@angular/core","name":"Injectable","line":20,"character":1}}],"members":{"__ctor__":[{"__symbolic":"constructor","parameters":[{"__symbolic":"reference","module":"../components/ng-searchbox.component","name":"NgSearchboxComponent","line":40,"character":22}]}],"getPublisher":[{"__symbolic":"method"}],"getFilterCount":[{"__symbolic":"method"}],"addOperatorToFilter":[{"__symbolic":"method"}],"hasOperatorAlready":[{"__symbolic":"method"}],"getOperators":[{"__symbolic":"method"}],"getFilters":[{"__symbolic":"method"}],"add":[{"__symbolic":"method"}],"removeByComponent":[{"__symbolic":"method"}],"setOperator":[{"__symbolic":"method"}],"getOperatorByFilterIndex":[{"__symbolic":"method"}],"remove":[{"__symbolic":"method"}],"removeAll":[{"__symbolic":"method"}],"buildExtendedParameter":[{"__symbolic":"method"}],"buildParameter":[{"__symbolic":"method"}],"update":[{"__symbolic":"method"}],"removeByFilterType":[{"__symbolic":"method"}]}}}}]